act4e_checks/__init__.py
act4e_checks/actual_tests.py
act4e_checks/currency_checks.py
act4e_checks/data.py
act4e_checks/intro.py
act4e_checks/loading.py
act4e_checks/maps.py
act4e_checks/posets_bounds.py
act4e_checks/posets_construction.py
act4e_checks/posets_interval.py
act4e_checks/posets_lattices.py
act4e_checks/posets_maps.py
act4e_checks/posets_monoidal.py
act4e_checks/posets_product.py
act4e_checks/posets_representation.py
act4e_checks/posets_sum.py
act4e_checks/posets_utils.py
act4e_checks/py.typed
act4e_checks/relations.py
act4e_checks/semicat_representation.py
act4e_checks/semigroups.py
act4e_checks/semigroups_morphisms_operations.py
act4e_checks/semigroups_morphisms_representation.py
act4e_checks/setoids_operations.py
act4e_checks/sets.py
act4e_checks/sets_power.py
act4e_checks/sets_product.py
act4e_checks/sets_representation.py
act4e_checks/sets_sum.py
act4e_checks/sets_union_inter.py
act4e_checks/sets_utils.py
act4e_checks/todo.py
act4e_checks/good/__init__.py
act4e_checks/good/finite_set.py
act4e_checks/good/finite_set_representation.py
act4e_checks/good/intro.py
act4e_checks/good/py.typed
act4e_checks/thedata/__init__.py
act4e_checks/thedata/categories.yaml
act4e_checks/thedata/categories_composite.yaml
act4e_checks/thedata/categories_curr.yaml
act4e_checks/thedata/dps.yaml
act4e_checks/thedata/dps_composite.yaml
act4e_checks/thedata/functors.yaml
act4e_checks/thedata/graphs.yaml
act4e_checks/thedata/maps.yaml
act4e_checks/thedata/natural.yaml
act4e_checks/thedata/posets.yaml
act4e_checks/thedata/posets_composite.yaml
act4e_checks/thedata/relations.yaml
act4e_checks/thedata/semigroups.yaml
act4e_checks/thedata/semigroups_morphisms.yaml
act4e_checks/thedata/sets.yaml
act4e_checks/thedata/sets_composite.yaml
act4e_interfaces/__init__.py
act4e_interfaces/adjunctions.py
act4e_interfaces/adjunctions_representation.py
act4e_interfaces/categories.py
act4e_interfaces/categories_monoidal.py
act4e_interfaces/categories_representation.py
ACT4E_exercises-7.3.2310261700.dist-info/METADATA
ACT4E_exercises-7.3.2310261700.dist-info/WHEEL
ACT4E_exercises-7.3.2310261700.dist-info/top_level.txt
ACT4E_exercises-7.3.2310261700.dist-info/zip-safe
ACT4E_exercises-7.3.2310261700.dist-info/RECORD
